rnadvisor/__init__.py
rnadvisor/cli_runner.py
rnadvisor/predict_abstract.py
rnadvisor/py.typed
rnadvisor/rnadvisor_cli.py
rnadvisor/enums/__init__.py
rnadvisor/enums/list_dockers.py
rnadvisor/metric/__init__.py
rnadvisor/metric/barnaba/__init__.py
rnadvisor/metric/barnaba/barnaba_helper.py
rnadvisor/metric/mcq4structures/__init__.py
rnadvisor/metric/mcq4structures/lcs_helper.py
rnadvisor/metric/mcq4structures/mcq_helper.py
rnadvisor/metric/open_structures/__init__.py
rnadvisor/metric/open_structures/abstract_ost.py
rnadvisor/metric/open_structures/lddt_helper.py
rnadvisor/metric/open_structures/tm_score_helper.py
rnadvisor/metric/rna_assessment/__init__.py
rnadvisor/metric/rna_assessment/abstract_assessment.py
rnadvisor/metric/rna_assessment/di_helper.py
rnadvisor/metric/rna_assessment/inf_helper.py
rnadvisor/metric/rna_assessment/p_value_helper.py
rnadvisor/metric/rna_assessment/rmsd_helper.py
rnadvisor/metric/voronota/__init__.py
rnadvisor/metric/voronota/cad_score_helper.py
rnadvisor/metric/zhanggroup/__init__.py
rnadvisor/metric/zhanggroup/gdt_ts_helper.py
rnadvisor/metric/zhanggroup/tm_score_helper.py
rnadvisor/scoring_function/__init__.py
rnadvisor/scoring_function/ares/__init__.py
rnadvisor/scoring_function/ares/ares_helper.py
rnadvisor/scoring_function/cgrnasp/__init__.py
rnadvisor/scoring_function/cgrnasp/cgrnasp_helper.py
rnadvisor/scoring_function/clash/__init__.py
rnadvisor/scoring_function/clash/clash_helper.py
rnadvisor/scoring_function/dfire/__init__.py
rnadvisor/scoring_function/dfire/dfire_helper.py
rnadvisor/scoring_function/lociparse/__init__.py
rnadvisor/scoring_function/lociparse/lociparse_helper.py
rnadvisor/scoring_function/pamnet/__init__.py
rnadvisor/scoring_function/pamnet/pamnet_helper.py
rnadvisor/scoring_function/rasp/__init__.py
rnadvisor/scoring_function/rasp/rasp_helper.py
rnadvisor/scoring_function/rna3dcnn/__init__.py
rnadvisor/scoring_function/rna3dcnn/rna3dcnn_helper.py
rnadvisor/scoring_function/rna_briq/__init__.py
rnadvisor-2.1.8.dist-info/METADATA
rnadvisor-2.1.8.dist-info/WHEEL
rnadvisor-2.1.8.dist-info/entry_points.txt
rnadvisor-2.1.8.dist-info/top_level.txt
rnadvisor-2.1.8.dist-info/RECORD
