Metadata-Version: 2.4
Name: rnadvisor
Version: 2.1.8
Summary: RNAdvisor is a wrapper tool to compute RNA 3D structure quality assessment.
Author-email: clementbernardd <clementbernardd@gmail.com>
Requires-Python: >=3.8
Requires-Dist: biopython>=1.83
Requires-Dist: click>=8.1.8
Requires-Dist: loguru>=0.7.3
Requires-Dist: pandas>=1.3.5
Requires-Dist: pyyaml>=6.0.2
Requires-Dist: rna-tools>=3.23.1
Requires-Dist: tqdm>=4.67.1
